port_scanner_test/__init__.py
port_scanner_test/monitoring.py
port_scanner_test/multiprocess_multithread.py
port_scanner_test-1.0.dist-info/LICENSE
port_scanner_test-1.0.dist-info/METADATA
port_scanner_test-1.0.dist-info/WHEEL
port_scanner_test-1.0.dist-info/top_level.txt
port_scanner_test-1.0.dist-info/RECORD
